Metadata-Version: 2.4
Name: adafruit-circuitpython-pcm51xx
Version: 1.0.1
Summary: CircuitPython driver for the Adafruit PCM51xx I2S DAC
Author-email: Adafruit Industries <circuitpython@adafruit.com>
License: MIT
Project-URL: Homepage, https://github.com/adafruit/Adafruit_CircuitPython_PCM51xx
Keywords: adafruit,blinka,circuitpython,micropython,pcm51xx,I2S,DAC,,PCM5122
Classifier: Intended Audience :: Developers
Classifier: Topic :: Software Development :: Libraries
Classifier: Topic :: Software Development :: Embedded Systems
Classifier: Topic :: System :: Hardware
Classifier: License :: OSI Approved :: MIT License
Classifier: Programming Language :: Python :: 3
License-File: LICENSE
Requires-Dist: Adafruit-Blinka
Requires-Dist: adafruit-circuitpython-busdevice
Provides-Extra: optional
Dynamic: license-file
